<annotation>
	<folder>collectedimages</folder>
	<filename>J3_jpg.rf.ff86dc5a870f1eadf471751c7fe11941.jpg</filename>
	<path>C:\Users\jasmin\Documents\RODPYTHON3.8\.venv\Scripts\RealTimeObjectDetection\Tensorflow\workspace\images\collectedimages\J3_jpg.rf.ff86dc5a870f1eadf471751c7fe11941.jpg</path>
	<source>
		<database>Unknown</database>
	</source>
	<size>
		<width>376</width>
		<height>376</height>
		<depth>3</depth>
	</size>
	<segmented>0</segmented>
	<object>
		<name>J</name>
		<pose>Unspecified</pose>
		<truncated>0</truncated>
		<difficult>0</difficult>
		<bndbox>
			<xmin>122</xmin>
			<ymin>165</ymin>
			<xmax>263</xmax>
			<ymax>268</ymax>
		</bndbox>
	</object>
</annotation>
